{
  "context": {
    "version": "2.0.0",
    "action": "discover",
    "domain": "beckn.one:retail",
    "bap_id": "sandbox-retail-np1.com",
    "bap_uri": "https://sandbox-retail-np1.com/bap",
    "transaction_id": "2cd192f6-ada6-4c61-b33a-3a31129d8e6a",
    "message_id": "24bb790c-88ad-40be-963b-18d9a94e2d52",
    "timestamp": "2025-01-27T10:00:00Z",
    "ttl": "PT30S",
    "schema_context": [
      "https://raw.githubusercontent.com/beckn/protocol-specifications-new/refs/heads/main/schema/GroceryItem/v1/context.jsonld"
    ]
  },
  "message": {
    "spatial": [
      {
        "op": "s_dwithin",
        "targets": "$['beckn:availableAt'][*]['geo']",
        "geometry": {
          "type": "Point",
          "coordinates": [
            77.5946,
            12.9716
          ]
        },
        "distanceMeters": 5000
      }
    ],
    "filters": {
      "type": "jsonpath",
      "expression": "$[?(@.beckn:itemAttributes.dietaryClassification == 'veg' && @.beckn:itemAttributes.category == 'PACKAGED_COMMODITIES')]"
    }
  }
}